README.md
setup.cfg
setup.py
wpscraper/__init__.py
wpscraper/datastores.py
wpscraper/test_wpscraper.py
wpscraper/wpscraper.py
wpscraper.egg-info/PKG-INFO
wpscraper.egg-info/SOURCES.txt
wpscraper.egg-info/dependency_links.txt
wpscraper.egg-info/not-zip-safe
wpscraper.egg-info/requires.txt
wpscraper.egg-info/top_level.txt