Metadata-Version: 1.0
Name: wpscraper
Version: 0.1
Summary: WordPress Site Recent Articles Scraper
Home-page: https://github.com/fayehall
Author: Faye Hall
Author-email: fayedaihall@mac.com
License: UNKNOWN
Platform: UNKNOWN
